Levenshtein/StringMatcher.py
Levenshtein/__init__.py
Levenshtein/_levenshtein.cp37-win_amd64.pyd
python_Levenshtein_wheels-0.13.2.dist-info/LICENSE
python_Levenshtein_wheels-0.13.2.dist-info/METADATA
python_Levenshtein_wheels-0.13.2.dist-info/WHEEL
python_Levenshtein_wheels-0.13.2.dist-info/top_level.txt
python_Levenshtein_wheels-0.13.2.dist-info/RECORD
