Metadata-Version: 1.2
Name: python-Levenshtein-wheels
Version: 0.13.2
Summary: Python extension for computing string edit distances and similarities.
Home-page: http://github.com/Tobotimus/python-Levenshtein
Author: Antti Haapala
Author-email: antti@haapala.name
Maintainer: Tobotimus
Maintainer-email: me@tobyharradine.id.au
License: GPL
Keywords: string Levenshtein comparison edit-distance
Platform: UNKNOWN
Classifier: License :: OSI Approved :: GNU General Public License v2 or later (GPLv2+)
Classifier: Programming Language :: C
Classifier: Programming Language :: Python
Classifier: Programming Language :: Python :: 2
Classifier: Programming Language :: Python :: 3
Classifier: Programming Language :: Python :: Implementation :: CPython
